watchmen_metricflow/__init__.py
watchmen_metricflow/app.py
watchmen_metricflow/cache/__init__.py
watchmen_metricflow/cache/metric_config_cache.py
watchmen_metricflow/duckdb/__init__.py
watchmen_metricflow/import/__init__.py
watchmen_metricflow/import/import_data_runner.py
watchmen_metricflow/main.py
watchmen_metricflow/meta/__init__.py
watchmen_metricflow/meta/data_profile_meta_service.py
watchmen_metricflow/meta/metrics_meta_service.py
watchmen_metricflow/meta/semantic_meta_service.py
watchmen_metricflow/metricflow/__init__.py
watchmen_metricflow/metricflow/config/__init__.py
watchmen_metricflow/metricflow/config/db_version/__init__.py
watchmen_metricflow/metricflow/config/db_version/cli_configuration_db.py
watchmen_metricflow/metricflow/config/db_version/dbt_artifacts_watchmen.py
watchmen_metricflow/metricflow/config/db_version/profile_load.py
watchmen_metricflow/metricflow/config/db_version/project_load.py
watchmen_metricflow/metricflow/config/parse/__init__.py
watchmen_metricflow/metricflow/config/parse/metric_parser.py
watchmen_metricflow/metricflow/config/parse/semantic_model_parser.py
watchmen_metricflow/metricflow/main_api.py
watchmen_metricflow/metricflow/meta_service.py
watchmen_metricflow/model/__init__.py
watchmen_metricflow/model/data_profile
watchmen_metricflow/model/data_profile.py
watchmen_metricflow/model/dbt_project.py
watchmen_metricflow/model/dimension_response.py
watchmen_metricflow/model/metric_request.py
watchmen_metricflow/model/metrics.py
watchmen_metricflow/model/semantic.py
watchmen_metricflow/router/__init__.py
watchmen_metricflow/router/data_profile_router.py
watchmen_metricflow/router/data_profle_router.py
watchmen_metricflow/router/metric_meta_router.py
watchmen_metricflow/router/metric_router.py
watchmen_metricflow/router/semantic_meta_router.py
watchmen_metricflow/router/topic_router.py
watchmen_metricflow/service/__init__.py
watchmen_metricflow/service/meta_service.py
watchmen_metricflow/settings.py
watchmen_metricflow-18.0.1.dist-info/METADATA
watchmen_metricflow-18.0.1.dist-info/WHEEL
watchmen_metricflow-18.0.1.dist-info/RECORD
